[
  {
    "id": "escrow_1",
    "projectId": "project_19",
    "projectTitle": "Brand Identity for Fashion Company",
    "client": {
      "id": "user_19",
      "name": "Kaća Kralj",
      "avatar": "https://randomuser.me/api/portraits/women/29.jpg",
      "email": "kaca.kralj@example.com"
    },
    "freelancer": {
      "id": "user_23",
      "name": "Albert Mccoy",
      "avatar": "https://randomuser.me/api/portraits/men/76.jpg",
      "email": "albert.mccoy@example.com"
    },
    "amount": 1050,
    "currency": "USD",
    "status": "released",
    "type": "full_payment",
    "createdAt": "2023-07-06T10:12:18.448Z",
    "releaseDate": "2025-08-26T16:38:21.596Z",
    "description": "Payment for Brand Identity for Fashion Company - Milestone 1",
    "milestoneNumber": 3,
    "disputeReason": null
  },
  {
    "id": "escrow_2",
    "projectId": "project_14",
    "projectTitle": "Logo Design for Technology Company",
    "client": {
      "id": "user_19",
      "name": "Kaća Kralj",
      "avatar": "https://randomuser.me/api/portraits/women/29.jpg",
      "email": "kaca.kralj@example.com"
    },
    "freelancer": {
      "id": "user_15",
      "name": "Pavitra Vernekar",
      "avatar": "https://randomuser.me/api/portraits/women/83.jpg",
      "email": "pavitra.vernekar@example.com"
    },
    "amount": 4983,
    "currency": "USD",
    "status": "pending",
    "type": "partial",
    "createdAt": "2023-02-08T05:32:23.842Z",
    "releaseDate": "2025-09-16T05:20:02.749Z",
    "description": "Payment for Logo Design for Technology Company - Milestone 2",
    "milestoneNumber": 4,
    "disputeReason": null
  },
  {
    "id": "escrow_3",
    "projectId": "project_30",
    "projectTitle": "Content Writing for Retail Company",
    "client": {
      "id": "user_13",
      "name": "Willow Evans",
      "avatar": "https://randomuser.me/api/portraits/women/7.jpg",
      "email": "willow.evans@example.com"
    },
    "freelancer": {
      "id": "user_18",
      "name": "Besim Lecomte",
      "avatar": "https://randomuser.me/api/portraits/men/79.jpg",
      "email": "besim.lecomte@example.com"
    },
    "amount": 2982,
    "currency": "USD",
    "status": "pending",
    "type": "partial",
    "createdAt": "2023-07-23T10:19:09.100Z",
    "releaseDate": "2025-09-16T07:00:05.582Z",
    "description": "Payment for Content Writing for Retail Company - Milestone 3",
    "milestoneNumber": 1,
    "disputeReason": null
  },
  {
    "id": "escrow_4",
    "projectId": "project_16",
    "projectTitle": "Website Design for Automotive Company",
    "client": {
      "id": "user_6",
      "name": "Sophia Gilbert",
      "avatar": "https://randomuser.me/api/portraits/women/43.jpg",
      "email": "sophia.gilbert@example.com"
    },
    "freelancer": {
      "id": "user_8",
      "name": "Sidraque Rodrigues",
      "avatar": "https://randomuser.me/api/portraits/men/27.jpg",
      "email": "sidraque.rodrigues@example.com"
    },
    "amount": 3734,
    "currency": "USD",
    "status": "active",
    "type": "partial",
    "createdAt": "2023-01-10T15:53:27.610Z",
    "releaseDate": "2025-08-08T03:39:50.148Z",
    "description": "Payment for Website Design for Automotive Company - Milestone 4",
    "milestoneNumber": 5,
    "disputeReason": null
  },
  {
    "id": "escrow_5",
    "projectId": "project_24",
    "projectTitle": "Web Development for Automotive Company",
    "client": {
      "id": "user_6",
      "name": "Sophia Gilbert",
      "avatar": "https://randomuser.me/api/portraits/women/43.jpg",
      "email": "sophia.gilbert@example.com"
    },
    "freelancer": {
      "id": "user_14",
      "name": "Dena Aragão",
      "avatar": "https://randomuser.me/api/portraits/women/86.jpg",
      "email": "dena.aragao@example.com"
    },
    "amount": 5145,
    "currency": "USD",
    "status": "active",
    "type": "partial",
    "createdAt": "2025-02-21T18:19:13.930Z",
    "releaseDate": "2025-07-18T23:42:03.831Z",
    "description": "Payment for Web Development for Automotive Company - Milestone 5",
    "milestoneNumber": 4,
    "disputeReason": null
  },
  {
    "id": "escrow_6",
    "projectId": "project_21",
    "projectTitle": "Video Production for Entertainment Company",
    "client": {
      "id": "user_22",
      "name": "Lucas Barbier",
      "avatar": "https://randomuser.me/api/portraits/men/64.jpg",
      "email": "lucas.barbier@example.com"
    },
    "freelancer": {
      "id": "user_9",
      "name": "Dora Pierce",
      "avatar": "https://randomuser.me/api/portraits/women/63.jpg",
      "email": "dora.pierce@example.com"
    },
    "amount": 3303,
    "currency": "USD",
    "status": "pending",
    "type": "partial",
    "createdAt": "2023-12-08T08:27:54.632Z",
    "releaseDate": "2025-09-16T20:05:25.754Z",
    "description": "Payment for Video Production for Entertainment Company - Milestone 6",
    "milestoneNumber": 5,
    "disputeReason": null
  },
  {
    "id": "escrow_7",
    "projectId": "project_23",
    "projectTitle": "SEO Optimization for Technology Company",
    "client": {
      "id": "user_24",
      "name": "Peter Burns",
      "avatar": "https://randomuser.me/api/portraits/men/81.jpg",
      "email": "peter.burns@example.com"
    },
    "freelancer": {
      "id": "user_15",
      "name": "Pavitra Vernekar",
      "avatar": "https://randomuser.me/api/portraits/women/83.jpg",
      "email": "pavitra.vernekar@example.com"
    },
    "amount": 2766,
    "currency": "USD",
    "status": "pending",
    "type": "partial",
    "createdAt": "2025-02-23T11:11:05.400Z",
    "releaseDate": "2025-07-05T13:26:27.026Z",
    "description": "Payment for SEO Optimization for Technology Company - Milestone 7",
    "milestoneNumber": 3,
    "disputeReason": null
  },
  {
    "id": "escrow_8",
    "projectId": "project_12",
    "projectTitle": "Content Writing for Automotive Company",
    "client": {
      "id": "user_22",
      "name": "Lucas Barbier",
      "avatar": "https://randomuser.me/api/portraits/men/64.jpg",
      "email": "lucas.barbier@example.com"
    },
    "freelancer": {
      "id": "user_18",
      "name": "Besim Lecomte",
      "avatar": "https://randomuser.me/api/portraits/men/79.jpg",
      "email": "besim.lecomte@example.com"
    },
    "amount": 3497,
    "currency": "USD",
    "status": "pending",
    "type": "full_payment",
    "createdAt": "2023-11-04T14:01:24.576Z",
    "releaseDate": "2025-08-10T01:47:20.425Z",
    "description": "Payment for Content Writing for Automotive Company - Milestone 8",
    "milestoneNumber": 4,
    "disputeReason": null
  },
  {
    "id": "escrow_9",
    "projectId": "project_29",
    "projectTitle": "Video Production for Real Estate Company",
    "client": {
      "id": "user_4",
      "name": "Teodoro Nogueira",
      "avatar": "https://randomuser.me/api/portraits/men/49.jpg",
      "email": "teodoro.nogueira@example.com"
    },
    "freelancer": {
      "id": "user_10",
      "name": "Alicia Laurent",
      "avatar": "https://randomuser.me/api/portraits/women/72.jpg",
      "email": "alicia.laurent@example.com"
    },
    "amount": 2565,
    "currency": "USD",
    "status": "active",
    "type": "milestone",
    "createdAt": "2024-02-11T08:26:49.482Z",
    "releaseDate": "2025-08-05T01:57:28.150Z",
    "description": "Payment for Video Production for Real Estate Company - Milestone 9",
    "milestoneNumber": 5,
    "disputeReason": null
  },
  {
    "id": "escrow_10",
    "projectId": "project_25",
    "projectTitle": "Brand Identity for Food & Beverage Company",
    "client": {
      "id": "user_22",
      "name": "Lucas Barbier",
      "avatar": "https://randomuser.me/api/portraits/men/64.jpg",
      "email": "lucas.barbier@example.com"
    },
    "freelancer": {
      "id": "user_3",
      "name": "Louka Deschamps",
      "avatar": "https://randomuser.me/api/portraits/men/6.jpg",
      "email": "louka.deschamps@example.com"
    },
    "amount": 4538,
    "currency": "USD",
    "status": "pending",
    "type": "full_payment",
    "createdAt": "2023-06-22T10:26:05.446Z",
    "releaseDate": "2025-08-23T14:18:43.821Z",
    "description": "Payment for Brand Identity for Food & Beverage Company - Milestone 10",
    "milestoneNumber": 1,
    "disputeReason": "Quality concerns"
  },
  {
    "id": "escrow_11",
    "projectId": "project_14",
    "projectTitle": "Logo Design for Technology Company",
    "client": {
      "id": "user_19",
      "name": "Kaća Kralj",
      "avatar": "https://randomuser.me/api/portraits/women/29.jpg",
      "email": "kaca.kralj@example.com"
    },
    "freelancer": {
      "id": "user_15",
      "name": "Pavitra Vernekar",
      "avatar": "https://randomuser.me/api/portraits/women/83.jpg",
      "email": "pavitra.vernekar@example.com"
    },
    "amount": 1865,
    "currency": "USD",
    "status": "released",
    "type": "partial",
    "createdAt": "2023-04-07T14:55:31.682Z",
    "releaseDate": "2025-06-25T10:33:57.749Z",
    "description": "Payment for Logo Design for Technology Company - Milestone 11",
    "milestoneNumber": 4,
    "disputeReason": null
  },
  {
    "id": "escrow_12",
    "projectId": "project_22",
    "projectTitle": "Photography for Food & Beverage Company",
    "client": {
      "id": "user_25",
      "name": "دینا نكو نظر",
      "avatar": "https://randomuser.me/api/portraits/women/15.jpg",
      "email": "dyn.nkwnzr@example.com"
    },
    "freelancer": {
      "id": "user_9",
      "name": "Dora Pierce",
      "avatar": "https://randomuser.me/api/portraits/women/63.jpg",
      "email": "dora.pierce@example.com"
    },
    "amount": 3103,
    "currency": "USD",
    "status": "active",
    "type": "full_payment",
    "createdAt": "2025-03-13T09:29:40.639Z",
    "releaseDate": "2025-07-13T20:39:54.496Z",
    "description": "Payment for Photography for Food & Beverage Company - Milestone 12",
    "milestoneNumber": 1,
    "disputeReason": "Quality concerns"
  },
  {
    "id": "escrow_13",
    "projectId": "project_26",
    "projectTitle": "Logo Design for Gaming Company",
    "client": {
      "id": "user_21",
      "name": "Cassandra Renard",
      "avatar": "https://randomuser.me/api/portraits/women/17.jpg",
      "email": "cassandra.renard@example.com"
    },
    "freelancer": {
      "id": "user_24",
      "name": "Peter Burns",
      "avatar": "https://randomuser.me/api/portraits/men/81.jpg",
      "email": "peter.burns@example.com"
    },
    "amount": 1838,
    "currency": "USD",
    "status": "disputed",
    "type": "milestone",
    "createdAt": "2025-03-17T15:31:31.789Z",
    "releaseDate": "2025-08-20T01:26:36.723Z",
    "description": "Payment for Logo Design for Gaming Company - Milestone 13",
    "milestoneNumber": 4,
    "disputeReason": null
  },
  {
    "id": "escrow_14",
    "projectId": "project_1",
    "projectTitle": "Photography for Food & Beverage Company",
    "client": {
      "id": "user_4",
      "name": "Teodoro Nogueira",
      "avatar": "https://randomuser.me/api/portraits/men/49.jpg",
      "email": "teodoro.nogueira@example.com"
    },
    "freelancer": {
      "id": "user_2",
      "name": "Miroslava Tarnovski",
      "avatar": "https://randomuser.me/api/portraits/women/38.jpg",
      "email": "miroslava.tarnovski@example.com"
    },
    "amount": 3453,
    "currency": "USD",
    "status": "active",
    "type": "milestone",
    "createdAt": "2024-01-31T08:22:20.729Z",
    "releaseDate": "2025-06-30T01:42:26.149Z",
    "description": "Payment for Photography for Food & Beverage Company - Milestone 14",
    "milestoneNumber": 4,
    "disputeReason": "Quality concerns"
  },
  {
    "id": "escrow_15",
    "projectId": "project_25",
    "projectTitle": "Brand Identity for Food & Beverage Company",
    "client": {
      "id": "user_22",
      "name": "Lucas Barbier",
      "avatar": "https://randomuser.me/api/portraits/men/64.jpg",
      "email": "lucas.barbier@example.com"
    },
    "freelancer": {
      "id": "user_3",
      "name": "Louka Deschamps",
      "avatar": "https://randomuser.me/api/portraits/men/6.jpg",
      "email": "louka.deschamps@example.com"
    },
    "amount": 4263,
    "currency": "USD",
    "status": "disputed",
    "type": "full_payment",
    "createdAt": "2024-11-12T05:42:40.547Z",
    "releaseDate": "2025-07-14T12:53:38.527Z",
    "description": "Payment for Brand Identity for Food & Beverage Company - Milestone 15",
    "milestoneNumber": 2,
    "disputeReason": null
  },
  {
    "id": "escrow_16",
    "projectId": "project_29",
    "projectTitle": "Video Production for Real Estate Company",
    "client": {
      "id": "user_4",
      "name": "Teodoro Nogueira",
      "avatar": "https://randomuser.me/api/portraits/men/49.jpg",
      "email": "teodoro.nogueira@example.com"
    },
    "freelancer": {
      "id": "user_10",
      "name": "Alicia Laurent",
      "avatar": "https://randomuser.me/api/portraits/women/72.jpg",
      "email": "alicia.laurent@example.com"
    },
    "amount": 5181,
    "currency": "USD",
    "status": "disputed",
    "type": "milestone",
    "createdAt": "2024-09-10T22:46:27.689Z",
    "releaseDate": "2025-08-05T08:25:01.067Z",
    "description": "Payment for Video Production for Real Estate Company - Milestone 16",
    "milestoneNumber": 3,
    "disputeReason": null
  },
  {
    "id": "escrow_17",
    "projectId": "project_21",
    "projectTitle": "Video Production for Entertainment Company",
    "client": {
      "id": "user_22",
      "name": "Lucas Barbier",
      "avatar": "https://randomuser.me/api/portraits/men/64.jpg",
      "email": "lucas.barbier@example.com"
    },
    "freelancer": {
      "id": "user_9",
      "name": "Dora Pierce",
      "avatar": "https://randomuser.me/api/portraits/women/63.jpg",
      "email": "dora.pierce@example.com"
    },
    "amount": 5211,
    "currency": "USD",
    "status": "active",
    "type": "partial",
    "createdAt": "2024-02-25T20:56:10.146Z",
    "releaseDate": "2025-07-11T01:39:51.186Z",
    "description": "Payment for Video Production for Entertainment Company - Milestone 17",
    "milestoneNumber": 2,
    "disputeReason": null
  },
  {
    "id": "escrow_18",
    "projectId": "project_9",
    "projectTitle": "E-commerce Store for Real Estate Company",
    "client": {
      "id": "user_20",
      "name": "Steven Hubert",
      "avatar": "https://randomuser.me/api/portraits/men/18.jpg",
      "email": "steven.hubert@example.com"
    },
    "freelancer": {
      "id": "user_25",
      "name": "دینا نكو نظر",
      "avatar": "https://randomuser.me/api/portraits/women/15.jpg",
      "email": "dyn.nkwnzr@example.com"
    },
    "amount": 2754,
    "currency": "USD",
    "status": "active",
    "type": "full_payment",
    "createdAt": "2025-04-24T16:05:16.034Z",
    "releaseDate": "2025-06-23T19:37:14.667Z",
    "description": "Payment for E-commerce Store for Real Estate Company - Milestone 18",
    "milestoneNumber": 5,
    "disputeReason": null
  },
  {
    "id": "escrow_19",
    "projectId": "project_10",
    "projectTitle": "Website Design for Food & Beverage Company",
    "client": {
      "id": "user_12",
      "name": "Minttu Laurila",
      "avatar": "https://randomuser.me/api/portraits/women/81.jpg",
      "email": "minttu.laurila@example.com"
    },
    "freelancer": {
      "id": "user_23",
      "name": "Albert Mccoy",
      "avatar": "https://randomuser.me/api/portraits/men/76.jpg",
      "email": "albert.mccoy@example.com"
    },
    "amount": 5344,
    "currency": "USD",
    "status": "active",
    "type": "milestone",
    "createdAt": "2024-12-17T05:44:05.927Z",
    "releaseDate": "2025-09-04T01:14:34.049Z",
    "description": "Payment for Website Design for Food & Beverage Company - Milestone 19",
    "milestoneNumber": 4,
    "disputeReason": null
  },
  {
    "id": "escrow_20",
    "projectId": "project_21",
    "projectTitle": "Video Production for Entertainment Company",
    "client": {
      "id": "user_22",
      "name": "Lucas Barbier",
      "avatar": "https://randomuser.me/api/portraits/men/64.jpg",
      "email": "lucas.barbier@example.com"
    },
    "freelancer": {
      "id": "user_9",
      "name": "Dora Pierce",
      "avatar": "https://randomuser.me/api/portraits/women/63.jpg",
      "email": "dora.pierce@example.com"
    },
    "amount": 3659,
    "currency": "USD",
    "status": "released",
    "type": "full_payment",
    "createdAt": "2023-08-14T11:55:00.935Z",
    "releaseDate": "2025-09-06T05:55:16.326Z",
    "description": "Payment for Video Production for Entertainment Company - Milestone 20",
    "milestoneNumber": 1,
    "disputeReason": null
  }
]